biliscribe/__init__.py
biliscribe/server.py
biliscribe-0.7.0.dist-info/METADATA
biliscribe-0.7.0.dist-info/WHEEL
biliscribe-0.7.0.dist-info/entry_points.txt
biliscribe-0.7.0.dist-info/RECORD
